{"dataZone":{"datazone":[false,false,false,false,false,false,false,false,false,false,false,false,false,false,false,false,false,false,false,false,false,false,false,false,false,false,false,false,false,false,false,false,false,false,false,false,false,false,false,false,false,false,false,false,false,false,false,false,false,false]},"PLCConnect":{"PLC_isconnected":true,"MQTT_isconnected":false,"Spinkler_isconnected":true},

"Historians":
{"historians":[
{"DATE":"19/11/2021","TIME":"10:29:17","ALARM":"RESET ALARM CENTER"},
{"DATE":"19/11/2021","TIME":"10:29:12","ALARM":"ZONE ALARM: Zone-1Zone-12"},
{"DATE":"19/11/2021","TIME":"10:29:06","ALARM":"ZONE ALARM: Zone-1"},
{"DATE":"19/11/2021","TIME":"10:29:02","ALARM":"RESET ALARM CENTER"},
{"DATE":"19/11/2021","TIME":"10:28:47","ALARM":"ZONE ALARM: Zone-13"},
{"DATE":"19/11/2021","TIME":"10:28:46","ALARM":"RESET ALARM CENTER"},
{"DATE":"19/11/2021","TIME":"10:28:45","ALARM":"ZONE ALARM: Zone-13Zone-16"},
{"DATE":"19/11/2021","TIME":"10:28:44","ALARM":"ZONE ALARM: Zone-15Zone-16"},
{"DATE":"19/11/2021","TIME":"10:28:40","ALARM":"ZONE ALARM: Zone-13Zone-15Zone-16"},
{"DATE":"19/11/2021","TIME":"10:28:39","ALARM":"ZONE ALARM: Zone-15Zone-16"},
{"DATE":"19/11/2021","TIME":"10:28:38","ALARM":"ZONE ALARM: Zone-13Zone-15Zone-16"},
{"DATE":"19/11/2021","TIME":"10:28:37","ALARM":"ZONE ALARM: Zone-15Zone-16"},
{"DATE":"19/11/2021","TIME":"10:28:36","ALARM":"ZONE ALARM: Zone-13Zone-15Zone-16"},
{"DATE":"19/11/2021","TIME":"10:28:35","ALARM":"ZONE ALARM: Zone-15Zone-16"},
{"DATE":"19/11/2021","TIME":"10:28:34","ALARM":"ZONE ALARM: Zone-13Zone-15Zone-16"},
{"DATE":"19/11/2021","TIME":"10:28:33","ALARM":"ZONE ALARM: Zone-15Zone-16"},
{"DATE":"19/11/2021","TIME":"10:19:25","ALARM":"ZONE ALARM: Zone-15Zone-16"},
{"DATE":"19/11/2021","TIME":"10:19:24","ALARM":"ZONE ALARM: Zone-13Zone-15Zone-16"},
{"DATE":"19/11/2021","TIME":"10:19:23","ALARM":"ZONE ALARM: Zone-15Zone-16"},
{"DATE":"19/11/2021","TIME":"10:19:22","ALARM":"ZONE ALARM: Zone-13Zone-15Zone-16"},
{"DATE":"19/11/2021","TIME":"10:19:21","ALARM":"ZONE ALARM: Zone-15Zone-16"},
{"DATE":"19/11/2021","TIME":"10:19:20","ALARM":"ZONE ALARM: Zone-13Zone-15Zone-16"},
{"DATE":"19/11/2021","TIME":"10:19:19","ALARM":"ZONE ALARM: Zone-15Zone-16"},
{"DATE":"19/11/2021","TIME":"10:19:17","ALARM":"ZONE ALARM: Zone-13Zone-15Zone-16"},
{"DATE":"19/11/2021","TIME":"10:19:16","ALARM":"ZONE ALARM: Zone-15Zone-16"},
{"DATE":"19/11/2021","TIME":"10:19:15","ALARM":"ZONE ALARM: Zone-13Zone-15Zone-16"},
{"DATE":"19/11/2021","TIME":"10:19:14","ALARM":"ZONE ALARM: Zone-15Zone-16"},
{"DATE":"19/11/2021","TIME":"10:19:13","ALARM":"ZONE ALARM: Zone-13Zone-15Zone-16"},
{"DATE":"19/11/2021","TIME":"10:19:12","ALARM":"ZONE ALARM: Zone-15Zone-16"},
{"DATE":"19/11/2021","TIME":"10:19:11","ALARM":"ZONE ALARM: Zone-13Zone-15Zone-16"},
{"DATE":"19/11/2021","TIME":"10:19:10","ALARM":"ZONE ALARM: Zone-15Zone-16"},
{"DATE":"19/11/2021","TIME":"10:19:08","ALARM":"ZONE ALARM: Zone-13Zone-15Zone-16"},
{"DATE":"19/11/2021","TIME":"10:19:07","ALARM":"ZONE ALARM: Zone-15Zone-16"},
{"DATE":"19/11/2021","TIME":"10:19:06","ALARM":"ZONE ALARM: Zone-13Zone-15Zone-16"},
{"DATE":"19/11/2021","TIME":"10:19:05","ALARM":"ZONE ALARM: Zone-15Zone-16"},
{"DATE":"19/11/2021","TIME":"10:19:04","ALARM":"ZONE ALARM: Zone-13Zone-15Zone-16"},
{"DATE":"19/11/2021","TIME":"10:19:03","ALARM":"ZONE ALARM: Zone-15Zone-16"},
{"DATE":"19/11/2021","TIME":"10:19:02","ALARM":"ZONE ALARM: Zone-13Zone-15Zone-16"},
{"DATE":"19/11/2021","TIME":"10:19:01","ALARM":"ZONE ALARM: Zone-15Zone-16"},
{"DATE":"19/11/2021","TIME":"10:18:59","ALARM":"ZONE ALARM: Zone-13Zone-15Zone-16"},
{"DATE":"19/11/2021","TIME":"10:18:58","ALARM":"ZONE ALARM: Zone-15Zone-16"},
{"DATE":"19/11/2021","TIME":"10:18:57","ALARM":"ZONE ALARM: Zone-13Zone-15Zone-16"},
{"DATE":"19/11/2021","TIME":"10:18:56","ALARM":"ZONE ALARM: Zone-15Zone-16"},
{"DATE":"19/11/2021","TIME":"10:18:55","ALARM":"ZONE ALARM: Zone-13Zone-15Zone-16"},
{"DATE":"19/11/2021","TIME":"10:18:54","ALARM":"ZONE ALARM: Zone-15Zone-16"},
{"DATE":"19/11/2021","TIME":"10:18:53","ALARM":"ZONE ALARM: Zone-13Zone-15Zone-16"},
{"DATE":"19/11/2021","TIME":"10:18:51","ALARM":"ZONE ALARM: Zone-15Zone-16"},
{"DATE":"19/11/2021","TIME":"10:18:51","ALARM":"ZONE ALARM: Zone-13Zone-15Zone-16"}]},

"dataW":{"Spinkler":5.3000001907348633,"PipeWall":5.5999999046325684},

"datadoor": {
    "Door1": 0,
    "Door2": 0,
    "Door3": 0,
    "Door4": 0,
    "Door5": 0,
    "Door6": 0,
    "Door7": 0,
    "Door8": 0,
    "Door9": 0,
    "Door10": 0,
    "Door11": 0
  },
"Timespan":"19/11/2021 11:12:16"}